conditional_cache/__init__.py
conditional_cache/conditional_cache.py
conditional_cache-1.4.dist-info/licenses/LICENSE
conditional_cache-1.4.dist-info/METADATA
conditional_cache-1.4.dist-info/WHEEL
conditional_cache-1.4.dist-info/top_level.txt
conditional_cache-1.4.dist-info/RECORD
